AUTHORS
ChangeLog.rst
HACKING
LICENSE
MANIFEST.in
README.rst
oonib.conf.example
requirements.txt
setup.py
bin/archive_oonib_reports
bin/oonib
bin/oonibadmin
data/bouncer.yaml
data/policy.yaml
data/archive/.gitignore
data/decks/README
data/inputs/Makefile
data/reports/.gitignore
data/reports/empty.txt
data/tor/.gitignore
oonib/__init__.py
oonib/api.py
oonib/config.py
oonib/daphn3.py
oonib/errors.py
oonib/handlers.py
oonib/log.py
oonib/onion.py
oonib/oonibackend.py
oonib/options.py
oonib/otime.py
oonib/bouncer/__init__.py
oonib/bouncer/api.py
oonib/bouncer/handlers.py
oonib/common/__init__.py
oonib/common/http_utils.py
oonib/common/ip_utils.py
oonib/common/tcp_utils.py
oonib/common/txextra.py
oonib/deck/__init__.py
oonib/deck/api.py
oonib/deck/handlers.py
oonib/input/__init__.py
oonib/input/api.py
oonib/input/handlers.py
oonib/main/__init__.py
oonib/main/api.py
oonib/main/handlers.py
oonib/policy/__init__.py
oonib/policy/api.py
oonib/policy/handlers.py
oonib/report/__init__.py
oonib/report/api.py
oonib/report/handlers.py
oonib/testhelpers/__init__.py
oonib/testhelpers/dns_helpers.py
oonib/testhelpers/http_helpers.py
oonib/testhelpers/ssl_helpers.py
oonib/testhelpers/tcp_helpers.py
oonib/tests/__init__.py
oonib/tests/handler_helpers.py
oonib/tests/test_bouncer.py
oonib/tests/test_global_handler.py
oonib/tests/test_report.py
oonib/tests/test_testhelpers.py
oonib/tests/test_web_connectivity.py
oonibackend.egg-info/PKG-INFO
oonibackend.egg-info/SOURCES.txt
oonibackend.egg-info/dependency_links.txt
oonibackend.egg-info/requires.txt
oonibackend.egg-info/top_level.txt